network_simulator/__init__.py
network_simulator/parameters.py
network_simulator/run_instances.py
network_simulator/test_private.py
network_simulator/yml_create_functions.py
network_simulator/get_data/__init__.py
network_simulator/get_data/get_data.py
network_simulator/gpt3_5/__init__.py
network_simulator/gpt3_5/gpt3_5.py
network_simulator/llama2/__init__.py
network_simulator/llama2/llama2.py
network_simulator/post/__init__.py
network_simulator/post/post.py
network_simulator/post/templates.py
network_simulator/post/transform_time.py
network_simulator/spelling_checker/__init__.py
network_simulator/spelling_checker/spelling_checker.py
network_simulator-1.0.1.dist-info/LICENCE.txt
network_simulator-1.0.1.dist-info/METADATA
network_simulator-1.0.1.dist-info/WHEEL
network_simulator-1.0.1.dist-info/top_level.txt
network_simulator-1.0.1.dist-info/RECORD
