Metadata-Version: 2.1
Name: network-simulator
Version: 1.0.1
Summary: Simulator that generates synthetic social network data
Home-page: https://github.com/minsoos/network_simulator
Author: Min Soo Jeon Acevedo
Author-email: mjeon@uc.cl
License: MIT
Classifier: Programming Language :: Python :: 3
Classifier: Operating System :: Microsoft :: Windows
Classifier: Operating System :: Unix
Classifier: Intended Audience :: Developers
Classifier: Intended Audience :: Science/Research
Classifier: Natural Language :: English
Classifier: Natural Language :: Spanish
Classifier: Topic :: Education
Classifier: Topic :: Scientific/Engineering :: Information Analysis
Classifier: License :: OSI Approved :: MIT License
Requires-Python: >=3.7
License-File: LICENCE.txt
Requires-Dist: Mesa==2.1.1
Requires-Dist: anytree>=2.8.0
Requires-Dist: soil==0.20.7
Requires-Dist: scipy>=1.8.0
Requires-Dist: numpy>=1.24.3
Requires-Dist: pyenchant>=3.2.2
Provides-Extra: llama2
Requires-Dist: torch>=2.1.2; extra == "llama2"
Requires-Dist: transformers>=4.36; extra == "llama2"
Requires-Dist: langchain>=0.0.352; extra == "llama2"
Provides-Extra: openai
Requires-Dist: openai>=1.6.1; extra == "openai"
